MANIFEST.in
Readme.rst
setup.py
CommonEnvironment_Formatter/__init__.py
CommonEnvironment_Formatter/__main__.py
CommonEnvironment_Formatter.egg-info/PKG-INFO
CommonEnvironment_Formatter.egg-info/SOURCES.txt
CommonEnvironment_Formatter.egg-info/dependency_links.txt
CommonEnvironment_Formatter.egg-info/entry_points.txt
CommonEnvironment_Formatter.egg-info/requires.txt
CommonEnvironment_Formatter.egg-info/top_level.txt
CommonEnvironment_Formatter/Plugins/PythonFormatter.py
CommonEnvironment_Formatter/Plugins/__init__.py
CommonEnvironment_Formatter/Plugins/PythonFormatterImpl/AlignAssignmentsPlugin.py
CommonEnvironment_Formatter/Plugins/PythonFormatterImpl/AlignTrailingCommentsPlugin.py
CommonEnvironment_Formatter/Plugins/PythonFormatterImpl/CommaAfterArgsPlugin.py
CommonEnvironment_Formatter/Plugins/PythonFormatterImpl/DebugPlugin.py
CommonEnvironment_Formatter/Plugins/PythonFormatterImpl/GroupEmptyParensPlugin.py
CommonEnvironment_Formatter/Plugins/PythonFormatterImpl/HorizontalAlignmentPluginImpl.py
CommonEnvironment_Formatter/Plugins/PythonFormatterImpl/PluginBase.py
CommonEnvironment_Formatter/Plugins/PythonFormatterImpl/SplitterPlugin.py
CommonEnvironment_Formatter/Plugins/PythonFormatterImpl/TextwrapDedentPlugin.py
CommonEnvironment_Formatter/Plugins/PythonFormatterImpl/__init__.py